alpa_conf/__init__.py
alpa_conf/alpa.py
alpa_conf/config_base.py
alpa_conf/constants.py
alpa_conf/exceptions.py
alpa_conf/metadata.py
alpa_conf-0.4.1.dist-info/LICENSE
alpa_conf-0.4.1.dist-info/METADATA
alpa_conf-0.4.1.dist-info/WHEEL
alpa_conf-0.4.1.dist-info/RECORD
